{
  "urldebasesiteweb": "https://xalimasn.com/",
  "imagesBaseSite": "",
  "description": "",
  "thematiqueSite": "",
  "sousCategorieSite": "",
  "contatcSite": "",
  "dateDernierTourSpider": "",
  "dateDernierTourCrawler": "",
  "javascript": "true",
  "contenuArticle": [
    {
      "noeudpere": "div",
      "proprietenoeudpere": "class",
      "valeurproprietenoeudpere": "td-post-content",
      "noeudfils": "",
      "contenurtxt": "p",
      "methode": "extraireContenuArticle"
    }
  ],
  "videosArticle": [
    {
      "noeudpere": "div",
      "proprietenoeudpere": "class",
      "valeurproprietenoeudpere": "wpb_video_wrapper",
      "noeudfils": "",
      "attribVideo": "src",
      "methode": "extraireVideosArticle"
    }
  ],
  "imagesArticle": [],
  "auteurArticle": [],
  "textHtmlElement": [],
  "thematiqueArticle": [],
  "valeurAttributNoeud": [],
  "sousCategorieArticle": [],
  "titreArticle": [],
  "resumeArticle": [],
  "datePublicationArticle": [
    {
      "noeudpere": "meta",
      "proprietenoeudpere": "itemprop",
      "valeurproprietenoeudpere": "datePublished",
      "niveau": 0,
      "niveauAttribut": 1,
      "methode": "extraireDatePublicationArticle"
    }
  ],
  "dateMiseJourArticle": [
    {
      "noeudpere": "meta",
      "proprietenoeudpere": "itemprop",
      "valeurproprietenoeudpere": "dateModified",
      "niveau": 0,
      "niveauAttribut": 1,
      "methode": "extraireDateMiseJourArticle"
    }
  ],
  "nombreLikesArticle": [],
  "nombreLecturesArticle": [],
  "nombreCommentairesArticle": [],
  "nombrePartagesArticle": [],
  "commentairesArticle": [],
  "motsClesArticle": [
    {
      "noeudpere": "ol",
      "proprietenoeudpere": "class",
      "valeurproprietenoeudpere": "comment-list",
      "noeudfils": "li",
      "methode": "extraireCommentairesArticle"
    }
  ]
}